pyvisfile/__init__.py
pyvisfile/py.typed
pyvisfile/vtk/__init__.py
pyvisfile/vtk/vtk_ordering.py
pyvisfile/xdmf/__init__.py
pyvisfile-2024.1.dist-info/LICENSE
pyvisfile-2024.1.dist-info/METADATA
pyvisfile-2024.1.dist-info/WHEEL
pyvisfile-2024.1.dist-info/top_level.txt
pyvisfile-2024.1.dist-info/RECORD
