Metadata-Version: 2.1
Name: pyvisfile
Version: 2024.1
Summary: Large-scale Visualization Data Storage
Author-email: Andreas Kloeckner <inform@tiker.net>
License: MIT
Project-URL: Documentation, https://documen.tician.de/pyvisfile
Project-URL: Homepage, https://mathema.tician.de/software/pyvisfile
Project-URL: Repository, https://github.com/inducer/pyvisfile
Classifier: Development Status :: 4 - Beta
Classifier: Intended Audience :: Developers
Classifier: Intended Audience :: Other Audience
Classifier: Intended Audience :: Science/Research
Classifier: License :: OSI Approved :: MIT License
Classifier: Natural Language :: English
Classifier: Programming Language :: C++
Classifier: Programming Language :: Python
Classifier: Programming Language :: Python :: 3 :: Only
Classifier: Topic :: Multimedia :: Graphics :: 3D Modeling
Classifier: Topic :: Scientific/Engineering
Classifier: Topic :: Scientific/Engineering :: Mathematics
Classifier: Topic :: Scientific/Engineering :: Physics
Classifier: Topic :: Scientific/Engineering :: Visualization
Classifier: Topic :: Software Development :: Libraries
Requires-Python: >=3.8
License-File: LICENSE
Requires-Dist: numpy
Requires-Dist: pytools >=2022.1
Provides-Extra: doc
Requires-Dist: furo ; extra == 'doc'
Requires-Dist: sphinx >=4 ; extra == 'doc'
Requires-Dist: sphinx-copybutton ; extra == 'doc'
Provides-Extra: test
Requires-Dist: mypy ; extra == 'test'
Requires-Dist: pytest ; extra == 'test'
Requires-Dist: ruff ; extra == 'test'
